swaybarclient/__init__.py
swaybarclient/swaybarclient.py
swaybarclient/modules/battery.py
swaybarclient/modules/cpu.py
swaybarclient/modules/time.py
swaybar_client-1.0.0.dist-info/LICENSE
swaybar_client-1.0.0.dist-info/METADATA
swaybar_client-1.0.0.dist-info/WHEEL
swaybar_client-1.0.0.dist-info/entry_points.txt
swaybar_client-1.0.0.dist-info/top_level.txt
swaybar_client-1.0.0.dist-info/RECORD
